LICENSE
MANIFEST.in
README.rst
requirements.txt
setup.py
emhub/__init__.py
emhub.egg-info/PKG-INFO
emhub.egg-info/SOURCES.txt
emhub.egg-info/dependency_links.txt
emhub.egg-info/entry_points.txt
emhub.egg-info/requires.txt
emhub.egg-info/top_level.txt
emhub/blueprints/__init__.py
emhub/blueprints/api.py
emhub/blueprints/images.py
emhub/blueprints/pages.py
emhub/client/__init__.py
emhub/client/__main__.py
emhub/client/cluster_lsf_worker.py
emhub/client/data_client.py
emhub/client/emh-worker-test.py
emhub/client/emhub_sessions_server.py
emhub/client/session_worker.py
emhub/client/worker.py
emhub/data/__init__.py
emhub/data/__main__.py
emhub/data/data_db.py
emhub/data/data_log.py
emhub/data/data_manager.py
emhub/data/data_models.py
emhub/data/models.py
emhub/data/content/__init__.py
emhub/data/content/dc_base.py
emhub/data/content/dc_bookings.py
emhub/data/content/dc_projects.py
emhub/data/content/dc_raw.py
emhub/data/content/dc_reports.py
emhub/data/content/dc_sessions.py
emhub/data/content/dc_users.py
emhub/data/imports/__init__.py
emhub/data/imports/scilifelab.py
emhub/data/imports/stjude.py
emhub/data/imports/stjude_smic.py
emhub/data/imports/stjude_xrc.py
emhub/data/imports/test.py
emhub/data/processing/__init__.py
emhub/data/processing/base.py
emhub/data/processing/processing_scipion.py
emhub/data/processing/processing_relion/__init__.py
emhub/data/processing/processing_relion/__main__.py
emhub/data/processing/processing_relion/parse_options_from_pipeline_jobs.py
emhub/data/processing/processing_relion/project.py
emhub/data/processing/processing_relion/runs.py
emhub/reports/__init__.py
emhub/reports/time_distribution.py
emhub/static/images/carbon-coater.png
emhub/static/images/down-arrow.png
emhub/static/images/drag-indicator.png
emhub/static/images/dropbox.png
emhub/static/images/emhub-sll.png
emhub/static/images/emhub-stjude.png
emhub/static/images/emhub-text-default.png
emhub/static/images/emhub-text.png
emhub/static/images/emhub.ico
emhub/static/images/emhub.png
emhub/static/images/leica-gp2.jpg
emhub/static/images/loader.svg
emhub/static/images/negstain-nook.png
emhub/static/images/switch.png
emhub/static/images/talos-artica.png
