Metadata-Version: 2.1
Name: emhub
Version: 1.0.2
Summary: Web application for monitoring EM results
Home-page: https://github.com/3dem/emhub
Author: J.M. De la Rosa Trevin, Grigory Sharov
Author-email: delarosatrevin@scilifelab.se, gsharov@mrc-lmb.cam.ac.uk
Project-URL: Bug Reports, https://github.com/3dem/emhub/issues
Project-URL: Source, https://github.com/3dem/emhub/
Classifier: Development Status :: 3 - Alpha
Classifier: License :: OSI Approved :: GNU General Public License v3 (GPLv3)
Classifier: Programming Language :: Python :: 3
License-File: LICENSE
Requires-Dist: click==8.1.6
Requires-Dist: emtools
Requires-Dist: Flask==2.3.2
Requires-Dist: Flask-Login==0.6.2
Requires-Dist: Flask-Mail==0.9.1
Requires-Dist: Flask-Markdown==0.3
Requires-Dist: gevent==23.7.0
Requires-Dist: greenlet==2.0.2
Requires-Dist: gunicorn==21.2.0
Requires-Dist: itsdangerous==2.1.2
Requires-Dist: Jinja2==3.1.2
Requires-Dist: Markdown==3.4.4
Requires-Dist: MarkupSafe==2.1.3
Requires-Dist: mrcfile
Requires-Dist: numpy==1.23.0
Requires-Dist: Pillow==9.2.0
Requires-Dist: psutil==5.9.1
Requires-Dist: PyJWT==2.8.0
Requires-Dist: tzlocal
Requires-Dist: pytz==2023.3
Requires-Dist: requests==2.28.1
Requires-Dist: SQLAlchemy==2.0.19
Requires-Dist: SQLAlchemy-Utc==0.14.0
Requires-Dist: Werkzeug==2.3.6
Requires-Dist: xmltodict==0.13.0
